designatedashboard/__init__.py
designatedashboard/sdk_connection.py
designatedashboard/api/__init__.py
designatedashboard/api/rest/__init__.py
designatedashboard/api/rest/designate.py
designatedashboard/dashboards/__init__.py
designatedashboard/dashboards/project/__init__.py
designatedashboard/dashboards/project/ngdns/__init__.py
designatedashboard/dashboards/project/ngdns/reverse_dns/__init__.py
designatedashboard/dashboards/project/ngdns/reverse_dns/panel.py
designatedashboard/dashboards/project/ngdns/reverse_dns/urls.py
designatedashboard/dashboards/project/ngdns/zones/__init__.py
designatedashboard/dashboards/project/ngdns/zones/panel.py
designatedashboard/dashboards/project/ngdns/zones/urls.py
designatedashboard/enabled/_1710_project_dns_panel_group.py
designatedashboard/enabled/_1721_dns_zones_panel.py
designatedashboard/enabled/_1722_dns_reversedns_panel.py
designatedashboard/enabled/__init__.py
designatedashboard/local_settings.d/_1799_dns_settings.py
designatedashboard/locale/cs/LC_MESSAGES/django.po
designatedashboard/locale/de/LC_MESSAGES/django.po
designatedashboard/locale/en_GB/LC_MESSAGES/django.po
designatedashboard/locale/es/LC_MESSAGES/django.po
designatedashboard/locale/fr/LC_MESSAGES/django.po
designatedashboard/locale/id/LC_MESSAGES/django.po
designatedashboard/locale/ja/LC_MESSAGES/django.po
designatedashboard/locale/ko_KR/LC_MESSAGES/django.po
designatedashboard/locale/ne/LC_MESSAGES/django.po
designatedashboard/locale/pt_BR/LC_MESSAGES/django.po
designatedashboard/locale/ru/LC_MESSAGES/django.po
designatedashboard/locale/tr_TR/LC_MESSAGES/django.po
designatedashboard/static/designatedashboard/designatedashboard.module.js
designatedashboard/static/designatedashboard/designatedashboard.scss
designatedashboard/static/designatedashboard/reverse_dns.html
designatedashboard/static/designatedashboard/zones.html
designatedashboard/static/designatedashboard/resources/resources.module.js
designate_dashboard-21.0.0.dist-info/AUTHORS
designate_dashboard-21.0.0.dist-info/LICENSE
designate_dashboard-21.0.0.dist-info/METADATA
designate_dashboard-21.0.0.dist-info/WHEEL
designate_dashboard-21.0.0.dist-info/pbr.json
designate_dashboard-21.0.0.dist-info/top_level.txt
designate_dashboard-21.0.0.dist-info/RECORD
